nonebot_paddle_ocr/__init__.py
nonebot_paddle_ocr/api_ocr.py
nonebot_paddle_ocr-1.1.1.dist-info/LICENSE.txt
nonebot_paddle_ocr-1.1.1.dist-info/METADATA
nonebot_paddle_ocr-1.1.1.dist-info/WHEEL
nonebot_paddle_ocr-1.1.1.dist-info/top_level.txt
nonebot_paddle_ocr-1.1.1.dist-info/RECORD
