Metadata-Version: 2.1
Name: nonebot-paddle-ocr
Version: 1.1.1
Summary: nonebot_paddle_ocr
Home-page: https://github.com/canxin121/nonebot_paddle_ocr
Author: canxin
Author-email: 1969730106@qq.com
Classifier: Programming Language :: Python :: 3.10
Classifier: Programming Language :: Python :: 3.8
Classifier: License :: OSI Approved :: GNU Affero General Public License v3
Classifier: Operating System :: OS Independent
License-File: LICENSE.txt
Requires-Dist: nonebot2 (>=2.0.0rc3)
Requires-Dist: nonebot-adapter-onebot (>=2.0.0b1)
Requires-Dist: requests (>=2.28.2)
Requires-Dist: paddlepaddle (>=2.4.2)
Requires-Dist: paddleocr (==2.6.1.3)
Requires-Dist: requests (==2.28.2)
Requires-Dist: PyMuPDF (==1.19.0)
